LICENSE
context_engine/__init__.py
context_engine/commands/command_map.py
context_engine/commands/components/__init__.py
context_engine/commands/components/all/__init__.py
context_engine/commands/expressions/__init__.py
context_engine/commands/expressions/all/__init__.py
context_engine/commands/expressions/new_dict_function.py
context_engine/commands/expressions/new_list_function.py
context_engine/commands/expressions/set_function.py
context_engine/commands/flows/__init__.py
context_engine/commands/flows/all/__init__.py
context_engine/commands/flows/block_logic.py
context_engine/commands/flows/do_while_logic.py
context_engine/commands/flows/foreach_logic.py
context_engine/commands/flows/if_logic.py
context_engine/commands/flows/try_logic.py
context_engine/commands/flows/while_logic.py
context_engine/decorators.py
context_engine/engine.py
context_engine-0.1.8.dist-info/LICENSE
context_engine-0.1.8.dist-info/WHEEL
context_engine-0.1.8.dist-info/METADATA
context_engine-0.1.8.dist-info/RECORD
