Metadata-Version: 2.1
Name: context-engine
Version: 0.1.8
Summary: Simple way to organize processing jobs. generally best when one or more specifications is involved.
Home-page: https://github.com/vkldwwk/context-engine
License: GPL-3.0-or-later
Keywords: context,engine,parser,specification,python
Author: vkldwwk
Author-email: jeff.elliott.dev@gmail.com
Requires-Python: >=3.9,<4.0
Classifier: Development Status :: 2 - Pre-Alpha
Classifier: Intended Audience :: Developers
Classifier: License :: OSI Approved :: GNU General Public License v3 or later (GPLv3+)
Classifier: Programming Language :: Python :: 3
Classifier: Programming Language :: Python :: 3.10
Classifier: Programming Language :: Python :: 3.9
Classifier: Topic :: Software Development :: Libraries :: Python Modules
Requires-Dist: ctx (>=0.1.2,<0.2.0)
Requires-Dist: decorator (==4.0.2)
Project-URL: Repository, https://github.com/vkldwwk/context-engine
